lektor_embed_x.py
lektor_embed_x-0.1.2.dist-info/DESCRIPTION.rst
lektor_embed_x-0.1.2.dist-info/METADATA
lektor_embed_x-0.1.2.dist-info/RECORD
lektor_embed_x-0.1.2.dist-info/WHEEL
lektor_embed_x-0.1.2.dist-info/entry_points.txt
lektor_embed_x-0.1.2.dist-info/metadata.json
lektor_embed_x-0.1.2.dist-info/top_level.txt
