Metadata-Version: 2.0
Name: lektor-embed-x
Version: 0.1.2
Summary: Enables embedding of web-contents from popular sites in MarkDown(*.md) on Lektor CMS
Home-page: https://github.com/kmonsoor/lektor-embed-x
Author: Khaled Monsoor
Author-email: k@kmonsoor.com
License: MIT
Keywords: lektor,embed,html,javascript,embeddable,code generation,from url
Platform: any
Classifier: Development Status :: 3 - Alpha
Classifier: Programming Language :: Python
Classifier: Environment :: Console
Classifier: Environment :: Web Environment
Classifier: Intended Audience :: Developers
Classifier: Operating System :: OS Independent
Classifier: License :: OSI Approved :: MIT License
Classifier: Topic :: Utilities
Classifier: Topic :: Software Development :: Libraries :: Python Modules
Requires-Dist: embedx
